{
  "name": "Translate an audio recording into a target-language transcript using Gladia and Google Drive",
  "nodes": [
    {
      "parameters": {
        "width": 480,
        "height": 600,
        "content": "## Translate an audio recording into a target-language transcript using Gladia and Google Drive\n\n### How it works\n\n1. Someone submits a form with a public audio or video URL and a target language code.\n2. The workflow sends that URL to Gladia and turns on transcription plus translation in one call.\n3. It polls Gladia until the job returns `done`, or stops on an error or timeout.\n4. A Code node builds a Markdown file holding the original transcript and the translation.\n5. The file is saved to Google Drive and a row is appended to a Google Sheet, with failures logged too.\n\n### Setup steps\n\n- [ ] Create a Header Auth credential named Gladia with header name x-gladia-key and your Gladia API key, then select it on both Gladia nodes.\n- [ ] Connect a Google Drive credential and set the Translations folder on Save Translation to Drive.\n- [ ] Connect a Google Sheets credential and pick the spreadsheet and tab on both Sheets nodes.\n- [ ] Open the form URL on the trigger and submit a public media URL to test.\n\n### Customization\n\nChange wait_seconds and max_attempts in Prepare Config Values to tune how long it polls, or edit the file layout in Build Translation File."
      },
      "id": "a0b1c2d3-0001-4a01-8a01-000000000001",
      "name": "Overview",
      "type": "n8n-nodes-base.stickyNote",
      "typeVersion": 1,
      "position": [-560, 100]
    },
    {
      "parameters": {
        "width": 740,
        "height": 240,
        "color": 7,
        "content": "## Receive request and start translation\n\nA form submission provides the media URL and target language, config values are prepared, then Gladia starts transcription with translation."
      },
      "id": "a0b1c2d3-0002-4a02-8a02-000000000002",
      "name": "Group Receive And Start",
      "type": "n8n-nodes-base.stickyNote",
      "typeVersion": 1,
      "position": [-40, 200]
    },
    {
      "parameters": {
        "width": 760,
        "height": 240,
        "color": 7,
        "content": "## Poll until translation completes\n\nWait, fetch the result, and route by status. Loop back until Gladia returns done or the attempt limit is reached."
      },
      "id": "a0b1c2d3-0003-4a03-8a03-000000000003",
      "name": "Group Poll For Result",
      "type": "n8n-nodes-base.stickyNote",
      "typeVersion": 1,
      "position": [720, 200]
    },
    {
      "parameters": {
        "width": 800,
        "height": 260,
        "color": 7,
        "content": "## Save and log the translation\n\nBuild a Markdown file with both transcripts, save it to Drive, and append a row to the log sheet."
      },
      "id": "a0b1c2d3-0004-4a04-8a04-000000000004",
      "name": "Group Save And Log",
      "type": "n8n-nodes-base.stickyNote",
      "typeVersion": 1,
      "position": [1500, 120]
    },
    {
      "parameters": {
        "width": 340,
        "height": 200,
        "color": 7,
        "content": "## Handle failures\n\nAny API error or a timeout writes a Failed row with a reason, so nothing fails silently."
      },
      "id": "a0b1c2d3-0005-4a05-8a05-000000000005",
      "name": "Group Handle Failures",
      "type": "n8n-nodes-base.stickyNote",
      "typeVersion": 1,
      "position": [1500, 420]
    },
    {
      "parameters": {
        "formTitle": "Translate an audio recording",
        "formDescription": "Paste a publicly reachable audio or video URL and choose a target language. You get back the original transcript and its translation.",
        "formFields": {
          "values": [
            {
              "fieldLabel": "Media URL",
              "fieldType": "text",
              "placeholder": "https://example.com/podcast-episode.mp3",
              "requiredField": true
            },
            {
              "fieldLabel": "Target language code",
              "fieldType": "text",
              "placeholder": "en",
              "requiredField": false
            }
          ]
        },
        "responseMode": "onReceived",
        "options": {
          "appendAttribution": false,
          "respondWithOptions": {
            "values": {
              "respondWith": "text",
              "formSubmittedText": "Thanks. Your recording is being transcribed and translated. When it finishes, the result is saved to your Google Drive and logged to your sheet. You can close this page."
            }
          }
        }
      },
      "id": "a0b1c2d3-0006-4a06-8a06-000000000006",
      "name": "When Translation Requested",
      "type": "n8n-nodes-base.formTrigger",
      "typeVersion": 2.6,
      "position": [40, 300],
      "webhookId": "b7e1c0a2-3d44-4f55-9a66-77c0a1b2c3d4"
    },
    {
      "parameters": {
        "assignments": {
          "assignments": [
            {
              "id": "f1a00001-0001-0001-0001-000000000001",
              "name": "media_url",
              "value": "={{ $json['Media URL'] }}",
              "type": "string"
            },
            {
              "id": "f1a00002-0002-0002-0002-000000000002",
              "name": "target_language",
              "value": "={{ ($json['Target language code'] || 'en').toString().trim().toLowerCase() }}",
              "type": "string"
            },
            {
              "id": "f1a00003-0003-0003-0003-000000000003",
              "name": "wait_seconds",
              "value": 10,
              "type": "number"
            },
            {
              "id": "f1a00004-0004-0004-0004-000000000004",
              "name": "max_attempts",
              "value": 60,
              "type": "number"
            }
          ]
        },
        "options": {}
      },
      "id": "a0b1c2d3-0007-4a07-8a07-000000000007",
      "name": "Prepare Config Values",
      "type": "n8n-nodes-base.set",
      "typeVersion": 3.4,
      "position": [280, 300]
    },
    {
      "parameters": {
        "method": "POST",
        "url": "https://api.gladia.io/v2/pre-recorded",
        "authentication": "genericCredentialType",
        "genericAuthType": "httpHeaderAuth",
        "sendBody": true,
        "contentType": "json",
        "specifyBody": "json",
        "jsonBody": "={{ { \"audio_url\": $('Prepare Config Values').item.json.media_url, \"translation\": true, \"translation_config\": { \"target_languages\": [$('Prepare Config Values').item.json.target_language] } } }}",
        "options": {
          "timeout": 30000
        }
      },
      "id": "a0b1c2d3-0008-4a08-8a08-000000000008",
      "name": "Start Gladia Translation",
      "type": "n8n-nodes-base.httpRequest",
      "typeVersion": 4.4,
      "position": [520, 300],
      "onError": "continueErrorOutput",
      "retryOnFail": true,
      "maxTries": 3,
      "waitBetweenTries": 5000,
      "credentials": {
        "httpHeaderAuth": {
          "id": "REPLACE_WITH_YOUR_GLADIA_CREDENTIAL",
          "name": "Gladia"
        }
      }
    },
    {
      "parameters": {
        "amount": "={{ $('Prepare Config Values').item.json.wait_seconds }}",
        "unit": "seconds"
      },
      "id": "a0b1c2d3-0009-4a09-8a09-000000000009",
      "name": "Wait for Processing",
      "type": "n8n-nodes-base.wait",
      "typeVersion": 1.1,
      "position": [780, 300],
      "webhookId": "c8f2d1b3-4e55-4a66-8b77-88d1b2c3d4e5"
    },
    {
      "parameters": {
        "url": "={{ $('Start Gladia Translation').item.json.result_url }}",
        "authentication": "genericCredentialType",
        "genericAuthType": "httpHeaderAuth",
        "options": {
          "timeout": 30000
        }
      },
      "id": "a0b1c2d3-0010-4a10-8a10-000000000010",
      "name": "Get Translation Result",
      "type": "n8n-nodes-base.httpRequest",
      "typeVersion": 4.4,
      "position": [1020, 300],
      "onError": "continueErrorOutput",
      "retryOnFail": true,
      "maxTries": 3,
      "waitBetweenTries": 5000,
      "credentials": {
        "httpHeaderAuth": {
          "id": "REPLACE_WITH_YOUR_GLADIA_CREDENTIAL",
          "name": "Gladia"
        }
      }
    },
    {
      "parameters": {
        "rules": {
          "values": [
            {
              "outputKey": "done",
              "conditions": {
                "options": {
                  "caseSensitive": true,
                  "leftValue": "",
                  "typeValidation": "strict"
                },
                "conditions": [
                  {
                    "leftValue": "={{ $json.status }}",
                    "rightValue": "done",
                    "operator": {
                      "type": "string",
                      "operation": "equals"
                    }
                  }
                ],
                "combinator": "and"
              }
            },
            {
              "outputKey": "failed",
              "conditions": {
                "options": {
                  "caseSensitive": true,
                  "leftValue": "",
                  "typeValidation": "loose"
                },
                "conditions": [
                  {
                    "leftValue": "={{ $json.status }}",
                    "rightValue": "error",
                    "operator": {
                      "type": "string",
                      "operation": "equals"
                    }
                  },
                  {
                    "leftValue": "={{ $runIndex }}",
                    "rightValue": "={{ $('Prepare Config Values').item.json.max_attempts }}",
                    "operator": {
                      "type": "number",
                      "operation": "gte"
                    }
                  }
                ],
                "combinator": "or"
              }
            }
          ]
        },
        "options": {
          "fallbackOutput": "extra",
          "renameFallbackOutput": "Still Processing"
        }
      },
      "id": "a0b1c2d3-0011-4a11-8a11-000000000011",
      "name": "Route by Status",
      "type": "n8n-nodes-base.switch",
      "typeVersion": 3.4,
      "position": [1280, 300]
    },
    {
      "parameters": {
        "mode": "runOnceForEachItem",
        "language": "javaScript",
        "jsCode": "// Build a Markdown file holding the original transcript and its translation.\n// Runs once per completed job (the Route by Status \"done\" output).\n\nconst result = $json.result || {};\nconst transcription = result.transcription || {};\nconst translation = result.translation || {};\n\nconst original = (transcription.full_transcript || '').trim();\nconst firstTranslation = (Array.isArray(translation.results) && translation.results[0]) || {};\nconst translated = (firstTranslation.full_transcript || '').trim();\n\n// Detected source language: first (most prevalent) entry in the languages array.\nconst detected = (Array.isArray(transcription.languages) && transcription.languages[0]) || 'unknown';\nconst target = $('Prepare Config Values').item.json.target_language || 'en';\nconst mediaUrl = $('Prepare Config Values').item.json.media_url || '';\n\nconst stamp = $now.toFormat('yyyyLLdd-HHmmss');\nconst fileName = 'translation-' + target + '-' + stamp + '.md';\n\nconst body = [\n  '# Audio translation',\n  '',\n  '- Source media: ' + mediaUrl,\n  '- Detected source language: ' + detected,\n  '- Target language: ' + target,\n  '- Translated: ' + $now.toISO(),\n  '',\n  '## Original transcript (' + detected + ')',\n  '',\n  original || '(No transcript text was returned.)',\n  '',\n  '## Translated transcript (' + target + ')',\n  '',\n  translated || '(No translation text was returned.)',\n  ''\n].join('\\n');\n\nreturn {\n  json: {\n    media_url: mediaUrl,\n    detected_language: detected,\n    target_language: target,\n    original_characters: original.length,\n    translated_characters: translated.length,\n    file_name: fileName,\n    preview: translated.slice(0, 180),\n  },\n  binary: {\n    data: {\n      data: Buffer.from(body, 'utf-8').toString('base64'),\n      mimeType: 'text/markdown',\n      fileName: fileName,\n      fileExtension: 'md',\n    },\n  },\n};"
      },
      "id": "a0b1c2d3-0012-4a12-8a12-000000000012",
      "name": "Build Translation File",
      "type": "n8n-nodes-base.code",
      "typeVersion": 2,
      "position": [1560, 220]
    },
    {
      "parameters": {
        "resource": "file",
        "operation": "upload",
        "name": "={{ $json.file_name }}",
        "driveId": {
          "__rl": true,
          "mode": "list",
          "value": "My Drive",
          "cachedResultName": "My Drive"
        },
        "folderId": {
          "__rl": true,
          "mode": "id",
          "value": "REPLACE_WITH_TRANSLATIONS_FOLDER_ID"
        },
        "inputDataFieldName": "data",
        "options": {}
      },
      "id": "a0b1c2d3-0013-4a13-8a13-000000000013",
      "name": "Save Translation to Drive",
      "type": "n8n-nodes-base.googleDrive",
      "typeVersion": 3,
      "position": [1800, 220],
      "onError": "continueErrorOutput",
      "credentials": {
        "googleDriveOAuth2Api": {
          "id": "REPLACE_WITH_YOUR_GOOGLE_DRIVE_CREDENTIAL",
          "name": "Google Drive account"
        }
      }
    },
    {
      "parameters": {
        "operation": "append",
        "documentId": {
          "__rl": true,
          "mode": "id",
          "value": "REPLACE_WITH_YOUR_SHEET_ID"
        },
        "sheetName": {
          "__rl": true,
          "mode": "list",
          "value": "REPLACE_WITH_SHEET_TAB",
          "cachedResultName": "Log"
        },
        "columns": {
          "mappingMode": "defineBelow",
          "value": {
            "Timestamp": "={{ $now.toISO() }}",
            "Media URL": "={{ $('Prepare Config Values').item.json.media_url }}",
            "Detected Language": "={{ $('Build Translation File').item.json.detected_language }}",
            "Target Language": "={{ $('Build Translation File').item.json.target_language }}",
            "Status": "Translated",
            "Translation Link": "={{ $json.webViewLink || 'https://drive.google.com/file/d/' + $json.id + '/view' }}",
            "Detail": "={{ $('Build Translation File').item.json.preview }}"
          },
          "matchingColumns": [],
          "schema": [
            {
              "id": "Timestamp",
              "displayName": "Timestamp",
              "required": false,
              "defaultMatch": false,
              "display": true,
              "type": "string",
              "canBeUsedToMatch": true
            },
            {
              "id": "Media URL",
              "displayName": "Media URL",
              "required": false,
              "defaultMatch": false,
              "display": true,
              "type": "string",
              "canBeUsedToMatch": true
            },
            {
              "id": "Detected Language",
              "displayName": "Detected Language",
              "required": false,
              "defaultMatch": false,
              "display": true,
              "type": "string",
              "canBeUsedToMatch": true
            },
            {
              "id": "Target Language",
              "displayName": "Target Language",
              "required": false,
              "defaultMatch": false,
              "display": true,
              "type": "string",
              "canBeUsedToMatch": true
            },
            {
              "id": "Status",
              "displayName": "Status",
              "required": false,
              "defaultMatch": false,
              "display": true,
              "type": "string",
              "canBeUsedToMatch": true
            },
            {
              "id": "Translation Link",
              "displayName": "Translation Link",
              "required": false,
              "defaultMatch": false,
              "display": true,
              "type": "string",
              "canBeUsedToMatch": true
            },
            {
              "id": "Detail",
              "displayName": "Detail",
              "required": false,
              "defaultMatch": false,
              "display": true,
              "type": "string",
              "canBeUsedToMatch": true
            }
          ]
        },
        "options": {}
      },
      "id": "a0b1c2d3-0014-4a14-8a14-000000000014",
      "name": "Log Translation in Sheets",
      "type": "n8n-nodes-base.googleSheets",
      "typeVersion": 4.7,
      "position": [2040, 220],
      "credentials": {
        "googleSheetsOAuth2Api": {
          "id": "REPLACE_WITH_YOUR_GOOGLE_SHEETS_CREDENTIAL",
          "name": "Google Sheets account"
        }
      }
    },
    {
      "parameters": {
        "operation": "append",
        "documentId": {
          "__rl": true,
          "mode": "id",
          "value": "REPLACE_WITH_YOUR_SHEET_ID"
        },
        "sheetName": {
          "__rl": true,
          "mode": "list",
          "value": "REPLACE_WITH_SHEET_TAB",
          "cachedResultName": "Log"
        },
        "columns": {
          "mappingMode": "defineBelow",
          "value": {
            "Timestamp": "={{ $now.toISO() }}",
            "Media URL": "={{ $('Prepare Config Values').first().json.media_url }}",
            "Detected Language": "",
            "Target Language": "={{ $('Prepare Config Values').first().json.target_language }}",
            "Status": "Failed",
            "Translation Link": "",
            "Detail": "={{ $json.error?.message || ($json.status ? ('Gladia status: ' + $json.status) : 'Translation failed or timed out. Check that the media URL is public, then retry.') }}"
          },
          "matchingColumns": [],
          "schema": [
            {
              "id": "Timestamp",
              "displayName": "Timestamp",
              "required": false,
              "defaultMatch": false,
              "display": true,
              "type": "string",
              "canBeUsedToMatch": true
            },
            {
              "id": "Media URL",
              "displayName": "Media URL",
              "required": false,
              "defaultMatch": false,
              "display": true,
              "type": "string",
              "canBeUsedToMatch": true
            },
            {
              "id": "Detected Language",
              "displayName": "Detected Language",
              "required": false,
              "defaultMatch": false,
              "display": true,
              "type": "string",
              "canBeUsedToMatch": true
            },
            {
              "id": "Target Language",
              "displayName": "Target Language",
              "required": false,
              "defaultMatch": false,
              "display": true,
              "type": "string",
              "canBeUsedToMatch": true
            },
            {
              "id": "Status",
              "displayName": "Status",
              "required": false,
              "defaultMatch": false,
              "display": true,
              "type": "string",
              "canBeUsedToMatch": true
            },
            {
              "id": "Translation Link",
              "displayName": "Translation Link",
              "required": false,
              "defaultMatch": false,
              "display": true,
              "type": "string",
              "canBeUsedToMatch": true
            },
            {
              "id": "Detail",
              "displayName": "Detail",
              "required": false,
              "defaultMatch": false,
              "display": true,
              "type": "string",
              "canBeUsedToMatch": true
            }
          ]
        },
        "options": {}
      },
      "id": "a0b1c2d3-0015-4a15-8a15-000000000015",
      "name": "Log Failure in Sheets",
      "type": "n8n-nodes-base.googleSheets",
      "typeVersion": 4.7,
      "position": [1560, 480],
      "credentials": {
        "googleSheetsOAuth2Api": {
          "id": "REPLACE_WITH_YOUR_GOOGLE_SHEETS_CREDENTIAL",
          "name": "Google Sheets account"
        }
      }
    }
  ],
  "connections": {
    "When Translation Requested": {
      "main": [
        [
          {
            "node": "Prepare Config Values",
            "type": "main",
            "index": 0
          }
        ]
      ]
    },
    "Prepare Config Values": {
      "main": [
        [
          {
            "node": "Start Gladia Translation",
            "type": "main",
            "index": 0
          }
        ]
      ]
    },
    "Start Gladia Translation": {
      "main": [
        [
          {
            "node": "Wait for Processing",
            "type": "main",
            "index": 0
          }
        ],
        [
          {
            "node": "Log Failure in Sheets",
            "type": "main",
            "index": 0
          }
        ]
      ]
    },
    "Wait for Processing": {
      "main": [
        [
          {
            "node": "Get Translation Result",
            "type": "main",
            "index": 0
          }
        ]
      ]
    },
    "Get Translation Result": {
      "main": [
        [
          {
            "node": "Route by Status",
            "type": "main",
            "index": 0
          }
        ],
        [
          {
            "node": "Log Failure in Sheets",
            "type": "main",
            "index": 0
          }
        ]
      ]
    },
    "Route by Status": {
      "main": [
        [
          {
            "node": "Build Translation File",
            "type": "main",
            "index": 0
          }
        ],
        [
          {
            "node": "Log Failure in Sheets",
            "type": "main",
            "index": 0
          }
        ],
        [
          {
            "node": "Wait for Processing",
            "type": "main",
            "index": 0
          }
        ]
      ]
    },
    "Build Translation File": {
      "main": [
        [
          {
            "node": "Save Translation to Drive",
            "type": "main",
            "index": 0
          }
        ]
      ]
    },
    "Save Translation to Drive": {
      "main": [
        [
          {
            "node": "Log Translation in Sheets",
            "type": "main",
            "index": 0
          }
        ],
        [
          {
            "node": "Log Failure in Sheets",
            "type": "main",
            "index": 0
          }
        ]
      ]
    }
  },
  "active": false,
  "settings": {
    "executionOrder": "v1"
  },
  "pinData": {},
  "meta": {
    "templateCredsSetupCompleted": false
  },
  "tags": []
}
